pdf_compressor/__init__.py
pdf_compressor/ilovepdf.py
pdf_compressor/main.py
pdf_compressor/utils.py
pdf_compressor-0.4.0.dist-info/METADATA
pdf_compressor-0.4.0.dist-info/WHEEL
pdf_compressor-0.4.0.dist-info/entry_points.txt
pdf_compressor-0.4.0.dist-info/top_level.txt
pdf_compressor-0.4.0.dist-info/RECORD
