Metadata-Version: 2.4
Name: pdf-compressor
Version: 0.4.0
Summary: CLI + Python API for batch compressing PDFs with iLovePDF.com
Author-email: Janosh Riebesell <janosh.riebesell@gmail.com>
License: MIT License
Project-URL: Homepage, https://github.com/janosh/pdf-compressor
Project-URL: Package, https://pypi.org/project/pdf-compressor
Keywords: cli,compression,ilovepdf,pdf
Classifier: License :: OSI Approved :: MIT License
Classifier: Programming Language :: Python :: 3 :: Only
Classifier: Programming Language :: Python :: 3
Classifier: Programming Language :: Python :: 3.11
Classifier: Programming Language :: Python :: 3.12
Classifier: Programming Language :: Python :: 3.13
Classifier: Programming Language :: Python :: 3.14
Requires-Python: >=3.11
Requires-Dist: requests>=2.25.0
Provides-Extra: test
Requires-Dist: pytest; extra == "test"
Requires-Dist: pytest-cov; extra == "test"
Provides-Extra: stats
Requires-Dist: pandas; extra == "stats"
